AUTHORS.rst
CHANGELOG.rst
LICENSE
MANIFEST.in
README.rst
setup.py
banner/__init__.py
banner/admin.py
banner/models.py
banner/styles.py
banner/urls.py
banner/views.py
banner/migrations/0001_initial.py
banner/migrations/0001_initial.pyc
banner/migrations/__init__.py
banner/migrations/__init__.pyc
banner/templates/banner/banner_detail.html
banner/templates/banner/banner_list.html
banner/templates/banner/inclusion_tags/banner_detail.html
banner/templatetags/__init__.py
banner/templatetags/__init__.pyc
banner/templatetags/banner_tags.py
banner/templatetags/banner_tags.pyc
banner/tests/__init__.py
banner/tests/__init__.pyc
banner/tests/manage.py
banner/tests/test_styles.py
banner/tests/test_styles.pyc
banner/tests/test_templatetags.py
banner/tests/test_templatetags.pyc
banner/tests/test_views.py
banner/tests/test_views.pyc
banner/tests/urls.py
banner/tests/urls.pyc
banner/tests/banner_config/__init__.py
banner/tests/banner_config/__init__.pyc
banner/tests/banner_config/styles.py
banner/tests/banner_config/styles.pyc
banner/tests/fixtures/sites.json
banner/tests/requirements/11.txt
banner/tests/res/image.jpg
banner/tests/settings/111.py
banner/tests/settings/111.pyc
banner/tests/settings/__init__.py
banner/tests/settings/__init__.pyc
banner/tests/templates/base.html
jmbo_banner.egg-info/PKG-INFO
jmbo_banner.egg-info/SOURCES.txt
jmbo_banner.egg-info/dependency_links.txt
jmbo_banner.egg-info/not-zip-safe
jmbo_banner.egg-info/requires.txt
jmbo_banner.egg-info/top_level.txt